d15/__init__.py
d15/about.py
d15/cli.py
d15/pipeline.py
d15/py.typed
d15/render.py
d15-1.0.1.dist-info/LICENSE
d15-1.0.1.dist-info/METADATA
d15-1.0.1.dist-info/WHEEL
d15-1.0.1.dist-info/entry_points.txt
d15-1.0.1.dist-info/top_level.txt
d15-1.0.1.dist-info/RECORD
