Metadata-Version: 2.1
Name: d15
Version: 1.0.1
Summary: D15 text-to-image model library
Home-page: https://github.com/justindujardin/d15
Author: Justin DuJardin
Author-email: justin@dujardinconsulting.com
License: Apache 2.0
Classifier: Development Status :: 3 - Alpha
Classifier: Intended Audience :: Developers
Classifier: Natural Language :: English
Classifier: License :: OSI Approved :: Apache Software License
Classifier: Operating System :: OS Independent
Classifier: Programming Language :: Python
Classifier: Programming Language :: Python :: 3.10
Classifier: Programming Language :: Python :: 3.11
Classifier: Programming Language :: Python :: 3.12
Requires-Python: >= 3.10
License-File: LICENSE
Requires-Dist: typer
Requires-Dist: pillow
Requires-Dist: torch>=2.0.0
Requires-Dist: diffusers>=0.32.0
Requires-Dist: transformers>=4.46.0
Requires-Dist: accelerate
